nprint/__init__.py
nprint/nprint.py
nprint-1.0.0.dist-info/DESCRIPTION.rst
nprint-1.0.0.dist-info/METADATA
nprint-1.0.0.dist-info/RECORD
nprint-1.0.0.dist-info/WHEEL
nprint-1.0.0.dist-info/metadata.json
nprint-1.0.0.dist-info/top_level.txt
