Metadata-Version: 2.0
Name: nprint
Version: 1.0.0
Summary: A lightweight nested printing, for all your function within loops within function needs
Home-page: https://github.com/joeyism/py-nprint
Author: Joey Sham
Author-email: sham.joey@gmail.com
License: UNKNOWN
Platform: UNKNOWN
